timings/mac.v
`timescale 1ns/1ps

// =======================================================
//  Pipelined MAC (DUT)
//    - 16x16 multiplier, 2-cycle pipeline
//    - 20-bit adder, 3-cycle pipeline
//    - ADD-only mode bypasses multiplier
// =======================================================
module pipelined_mac (
    input         clk,
    input         rst,        // active high

    // control
    input         mode_add,   // 0 = MAC (mul+add), 1 = ADD-only
    input         mux_sel,    // 0 = use 0, 1 = use ACC feedback
    input         in_valid,   // start a MAC operation
    input         add_valid,  // start an ADD-only operation

    // data
    input  [15:0] a,
    input  [15:0] b,
    input  [19:0] add_in,

    output reg [19:0] acc,          // accumulate register
    output reg        mac_done,     // 1 when MAC result writes ACC
    output reg        add_done      // 1 when ADD result writes ACC
);

    // ---------------- Multiplier: 2-cycle pipeline ----------------
    reg [15:0] a_reg, b_reg;
    reg [31:0] mul_s1, mul_s2;

    // ---------------- Adder: 3-cycle pipeline --------------------
    reg [19:0] add_s1, add_s2, add_s3;

    // Valid pipelines
    reg [4:0] mac_valid_pipe;   // 5-cycle MAC latency
    reg [2:0] add_valid_pipe;   // 3-cycle ADD-only latency

    // Operand select going into adder
    wire [19:0] op_sel    = mode_add ? add_in : mul_s2[19:0];

    // ACC feedback or zero
    wire [19:0] acc_src   = mux_sel ? acc : 20'd0;

    always @(posedge clk) begin
        if (rst) begin
            a_reg          <= 16'd0;
            b_reg          <= 16'd0;
            mul_s1         <= 32'd0;
            mul_s2         <= 32'd0;
            add_s1         <= 20'd0;
            add_s2         <= 20'd0;
            add_s3         <= 20'd0;
            acc            <= 20'd0;
            mac_valid_pipe <= 5'd0;
            add_valid_pipe <= 3'd0;
            mac_done       <= 1'b0;
            add_done       <= 1'b0;
        end else begin
            // valid shift registers
            mac_valid_pipe <= {mac_valid_pipe[3:0], in_valid};
            add_valid_pipe <= {add_valid_pipe[1:0], add_valid};

            // multiplier pipeline (2 cycles)
            if (in_valid) begin
                a_reg <= a;
                b_reg <= b;
            end
            mul_s1 <= a_reg * b_reg;
            mul_s2 <= mul_s1;

            // adder pipeline (3 cycles)
            add_s1 <= acc_src + op_sel;
            add_s2 <= add_s1;
            add_s3 <= add_s2;

            // pop valid bits
            mac_done <= mac_valid_pipe[4];
            add_done <= add_valid_pipe[2];

            // write ACC
            if (mac_valid_pipe[4] || add_valid_pipe[2]) begin
                acc <= add_s3;
            end
        end
    end

endmodule

timings/mac_tb.v
`timescale 1ns/1ps

module tb;

    reg         clk;
    reg         rst;
    reg         mode_add;
    reg         mux_sel;
    reg         in_valid;
    reg         add_valid;
    reg  [15:0] a;
    reg  [15:0] b;
    reg  [19:0] add_in;

    wire [19:0] acc;
    wire        mac_done;
    wire        add_done;

    // ---------------- Instantiate DUT ----------------
    pipelined_mac dut (
        .clk(clk),
        .rst(rst),
        .mode_add(mode_add),
        .mux_sel(mux_sel),
        .in_valid(in_valid),
        .add_valid(add_valid),
        .a(a),
        .b(b),
        .add_in(add_in),
        .acc(acc),
        .mac_done(mac_done),
        .add_done(add_done)
    );

    // ---------------- Clock ----------------
    initial begin
        clk = 0;
        forever #5 clk = ~clk;   // 10 ns clock
    end

    integer cycle;

    // ---------------- Stimulus ----------------
    initial begin
        $dumpfile("mac_timing.vcd");
        $dumpvars(0, tb);

        // defaults
        rst       = 1;
        mode_add  = 0;
        mux_sel   = 0;
        in_valid  = 0;
        add_valid = 0;
        a         = 0;
        b         = 0;
        add_in    = 0;
        cycle     = -1;

        repeat (15) begin
            @(posedge clk);
            cycle = cycle + 1;

            case (cycle)
                // 0–1 : reset high
                0,1: begin
                    rst       <= 1;
                    in_valid  <= 0;
                    add_valid <= 0;
                    mux_sel   <= 0;
                    mode_add  <= 0;
                end

                // 2 : release reset
                2: begin
                    rst <= 0;
                end

                // -------- MAC OPERATION (mul+add) --------
                // Start MAC at cycle 3: ACC = (3 * 5)
                3: begin
                    mode_add  <= 0;     // MAC mode
                    mux_sel   <= 0;     // ACC reset
                    in_valid  <= 1;
                    a         <= 16'd3;
                    b         <= 16'd5;
                end

                4: in_valid <= 0;       // pipelining continues

                // 5–8: internal pipeline running (mult+adder)
                5,6,7,8: begin end

                // -------- ADD-ONLY OP (ACC + 7) --------
                9: begin
                    mode_add  <= 1;
                    mux_sel   <= 1;
                    add_in    <= 20'd7;
                    add_valid <= 1;
                end

                10: add_valid <= 0;

                // pipeline 11

                // -------- small reset section --------
                12: rst <= 1;
                13: rst <= 0;

                // 14: idle
                14: begin
                    mode_add  <= 0;
                    mux_sel   <= 0;
                    in_valid  <= 0;
                    add_valid <= 0;
                end
            endcase
        end

        @(posedge clk);
        $finish;
    end

endmodule

timings/mac_timing.vcd
$date
	Sun Dec  7 05:44:49 2025
$end
$version
	Icarus Verilog
$end
$timescale
	1ps
$end
$scope module tb $end
$var wire 1 ! mac_done $end
$var wire 1 " add_done $end
$var wire 20 # acc [19:0] $end
$var reg 16 $ a [15:0] $end
$var reg 20 % add_in [19:0] $end
$var reg 1 & add_valid $end
$var reg 16 ' b [15:0] $end
$var reg 1 ( clk $end
$var reg 1 ) in_valid $end
$var reg 1 * mode_add $end
$var reg 1 + mux_sel $end
$var reg 1 , rst $end
$var integer 32 - cycle [31:0] $end
$scope module dut $end
$var wire 16 . a [15:0] $end
$var wire 20 / add_in [19:0] $end
$var wire 1 & add_valid $end
$var wire 16 0 b [15:0] $end
$var wire 1 ( clk $end
$var wire 1 ) in_valid $end
$var wire 1 * mode_add $end
$var wire 1 + mux_sel $end
$var wire 1 , rst $end
$var wire 20 1 op_sel [19:0] $end
$var wire 20 2 acc_src [19:0] $end
$var reg 16 3 a_reg [15:0] $end
$var reg 20 4 acc [19:0] $end
$var reg 1 " add_done $end
$var reg 20 5 add_s1 [19:0] $end
$var reg 20 6 add_s2 [19:0] $end
$var reg 20 7 add_s3 [19:0] $end
$var reg 3 8 add_valid_pipe [2:0] $end
$var reg 16 9 b_reg [15:0] $end
$var reg 1 ! mac_done $end
$var reg 5 : mac_valid_pipe [4:0] $end
$var reg 32 ; mul_s1 [31:0] $end
$var reg 32 < mul_s2 [31:0] $end
$upscope $end
$upscope $end
$enddefinitions $end
$comment Show the parameter values. $end
$dumpall
$end
#0
$dumpvars
bx <
bx ;
bx :
bx 9
bx 8
bx 7
bx 6
bx 5
bx 4
bx 3
b0 2
bx 1
b0 0
b0 /
b0 .
b11111111111111111111111111111111 -
1,
0+
0*
0)
0(
b0 '
0&
b0 %
b0 $
bx #
x"
x!
$end
#5000
b0 1
0"
0!
b0 8
b0 :
b0 #
b0 4
b0 7
b0 6
b0 5
b0 <
b0 ;
b0 9
b0 3
b0 -
1(
#10000
0(
#15000
b1 -
1(
#20000
0(
#25000
0,
b10 -
1(
#30000
0(
#35000
b101 '
b101 0
b11 $
b11 .
1)
b11 -
1(
#40000
0(
#45000
b101 9
b11 3
b1 :
0)
b100 -
1(
#50000
0(
#55000
b1111 ;
b10 :
b101 -
1(
#60000
0(
#65000
b1111 1
b1111 <
b100 :
b110 -
1(
#70000
0(
#75000
b1111 5
b1000 :
b111 -
1(
#80000
0(
#85000
b1111 6
b10000 :
b1000 -
1(
#90000
0(
#95000
b111 1
1&
b111 %
b111 /
1+
1*
1!
b1111 7
b0 :
b1001 -
1(
#100000
0(
#105000
0!
b111 5
b1 8
0&
b1010 -
1(
#110000
0(
#115000
b111 6
b10 8
b1011 -
1(
#120000
0(
#125000
b111 7
b100 8
1,
b1100 -
1(
#130000
0(
#135000
0,
b0 8
b0 7
b0 6
b0 5
b0 <
b0 ;
b0 9
b0 3
b1101 -
1(
#140000
0(
#145000
b0 1
b111 5
0+
0*
b1110 -
1(
#150000
0(
#155000
b111 6
b0 5
1(
