timings/mac.v
module mac (
    input clk,
    input rst,
    input [7:0] a,
    input [7:0] w,
    input [19:0] in_ad,
    input mux_sel_g,      // 1: bypass multiplier, use in_ad; 0: use multiplier output
    input mux_sel,        // 1: use accumulator feedback; 0: clear (use 0)
    output reg [19:0] accumulate
);

reg [2:0] count;
wire [2:0] next_count;

assign next_count = (count == 3'd4) ? 3'b000 : count + 1'b1;


reg [19:0] out_mult;
wire [19:0] next_acc,acc_check;
wire [19:0] in_add, next_mult;

always@(posedge clk) begin
    if (rst) begin
        count <= 3'b0;
    end else begin
        count <= next_count;
    end
end

assign next_mult  = (count == 3'd1) ? {4'b0000,(a * w)} : out_mult;
assign next_acc   = (count == 3'd4) ? in_add + acc_check : accumulate;

always@(posedge clk) begin
    if (rst) begin
        out_mult <= 20'b0;
    end else begin
        out_mult <= next_mult;
    end
end

always@(posedge clk) begin
    if (rst) begin
        accumulate <= 20'b0;
    end else begin
        accumulate <= next_acc;
    end
end

assign acc_check = mux_sel ? accumulate : 20'b0;
assign in_add = mux_sel_g? in_ad : out_mult;

endmodule

timings/mac_tb.v
// Testbench for MAC module
`timescale 1ns/1ps

module mac_tb;
    reg clk;
    reg rst;
    reg [7:0] a;
    reg [7:0] w;
    reg [19:0] in_ad;
    reg mux_sel_g;
    reg mux_sel;
    wire [19:0] accumulate;

    integer cycle_count;

    // Instantiate MAC module (match ports in mac.v)
    mac dut (
        .clk(clk),
        .rst(rst),
        .a(a),
        .w(w),
        .in_ad(in_ad),
        .mux_sel_g(mux_sel_g),
        .mux_sel(mux_sel),
        .accumulate(accumulate)
    );

    // Clock generation (10ns period)
    initial begin
        clk = 0;
        forever #5 clk = ~clk;
    end

    // Cycle counter
    initial begin
        cycle_count = 0;
        forever @(posedge clk) cycle_count = cycle_count + 1;
    end

    // Test sequence: exercise multiply, accumulate, and bypass paths
    initial begin
        // Initialize
        rst = 1;
        a = 0;
        w = 0;
        in_ad = 0;
        mux_sel_g = 0;
        mux_sel = 0;

        // Hold reset for a couple cycles
        @(posedge clk);
        @(posedge clk);
        rst = 0;

        // --- Test 1: simple multiply (3 * 5) with accumulator cleared ---
        // Set mux_sel_g=0 (use multiplier), mux_sel=0 (clear accumulator)
        a = 8'd3;
        w = 8'd5;
        mux_sel_g = 0;
        mux_sel = 0;

        // Wait enough cycles for pipeline (mult and two-stage add pipeline -> 4-5 cycles)
        repeat (5) @(posedge clk);
        $display("[Test1] Expected product=15 (shifted into 20-bit), accumulate=%0d", accumulate);

        // --- Test 2: accumulate second product (2 * 3) on top of previous ---
        // First ensure pipeline cleared input, then feed second product with mux_sel=1
        a = 8'd2;
        w = 8'd3;
        mux_sel_g = 0; // still use multiplier
        mux_sel = 1;   // use accumulator feedback

        // Wait pipeline
        repeat (5) @(posedge clk);
        $display("[Test2] After accumulating 2*3, accumulate=%0d (expected previous + 6)", accumulate);

        // --- Test 3: bypass adder input using in_ad ---
        // Provide a direct addend of 4 via in_ad and keep mux_sel=1 to add to current accumulator
        in_ad = 20'd4;
        mux_sel_g = 1; // bypass multiplier, use in_ad
        mux_sel = 1;   // keep accumulating

        repeat (5) @(posedge clk);
        $display("[Test3] After bypass add of 4, accumulate=%0d (expected previous + 4)", accumulate);

        // --- Test 4: reset and verify accumulate cleared ---
        repeat (3) @(posedge clk);
        $display("[Test4] After reset, accumulate=%0d (expected 0)", accumulate);

        $finish;
    end

    // VCD dump
    initial begin
        $dumpfile("mac_timing.vcd");
        $dumpvars(0, mac_tb, dut);
    end

    // Monitor
    always @(posedge clk) begin
        $display("C=%0d T=%0t rst=%b a=%0d w=%0d in_ad=%0d mux_sel_g=%b mux_sel=%b acc=%0d",
                 cycle_count, $time, rst, a, w, in_ad, mux_sel_g, mux_sel, accumulate);
    end

endmodule

timings/mac_timing.vcd
$date
	Mon Dec  8 11:27:54 2025
$end
$version
	Icarus Verilog
$end
$timescale
	1ps
$end
$scope module mac_tb $end
$var wire 20 ! accumulate [19:0] $end
$var reg 8 " a [7:0] $end
$var reg 1 # clk $end
$var reg 20 $ in_ad [19:0] $end
$var reg 1 % mux_sel $end
$var reg 1 & mux_sel_g $end
$var reg 1 ' rst $end
$var reg 8 ( w [7:0] $end
$var integer 32 ) cycle_count [31:0] $end
$scope module dut $end
$var wire 8 * a [7:0] $end
$var wire 1 # clk $end
$var wire 20 + in_ad [19:0] $end
$var wire 1 % mux_sel $end
$var wire 1 & mux_sel_g $end
$var wire 1 ' rst $end
$var wire 8 , w [7:0] $end
$var wire 20 - next_mult [19:0] $end
$var wire 3 . next_count [2:0] $end
$var wire 20 / next_acc [19:0] $end
$var wire 20 0 in_add [19:0] $end
$var wire 20 1 acc_check [19:0] $end
$var reg 20 2 accumulate [19:0] $end
$var reg 3 3 count [2:0] $end
$var reg 20 4 out_mult [19:0] $end
$upscope $end
$upscope $end
$scope module mac_tb $end
$scope module dut $end
$upscope $end
$upscope $end
$enddefinitions $end
$comment Show the parameter values. $end
$dumpall
$end
#0
$dumpvars
bx 4
bx 3
bx 2
b0 1
bx 0
bx /
bx .
bx -
b0 ,
b0 +
b0 *
b0 )
b0 (
1'
0&
0%
b0 $
0#
b0 "
bx !
$end
#5000
b1 .
b0 -
b0 0
b0 /
b0 3
b0 4
b0 !
b0 2
b1 )
1#
#10000
0#
#15000
b101 (
b101 ,
b11 "
b11 *
0'
b10 )
1#
#20000
0#
#25000
b10 .
b1111 -
b1 3
b11 )
1#
#30000
0#
#35000
b1111 0
b11 .
b1111 4
b10 3
b100 )
1#
#40000
0#
#45000
b100 .
b11 3
b101 )
1#
#50000
0#
#55000
b0 .
b1111 /
b100 3
b110 )
1#
#60000
0#
#65000
b1 .
b1111 1
b0 3
b1111 !
b1111 2
b111 )
1%
b11 (
b11 ,
b10 "
b10 *
1#
#70000
0#
#75000
b10 .
b110 -
b1 3
b1000 )
1#
#80000
0#
#85000
b11 .
b110 0
b10 3
b110 4
b1001 )
1#
#90000
0#
#95000
b100 .
b11 3
b1010 )
1#
#100000
0#
#105000
b0 .
b10101 /
b100 3
b1011 )
1#
#110000
0#
#115000
b10101 1
b1 .
b10101 !
b10101 2
b0 3
b10101 /
b100 0
1&
b100 $
b100 +
b1100 )
1#
#120000
0#
#125000
b10 .
b1 3
b1101 )
1#
#130000
0#
#135000
b11 .
b10 3
b1110 )
1#
#140000
0#
#145000
b100 .
b11 3
b1111 )
1#
#150000
0#
#155000
b0 .
b11001 /
b100 3
b10000 )
1#
#160000
0#
#165000
b1 .
b11001 1
b0 3
b11001 !
b11001 2
b10001 )
1#
#170000
0#
#175000
b10 .
b1 3
b10010 )
1#
#180000
0#
#185000
b11 .
b10 3
b10011 )
1#
#190000
0#
#195000
b100 .
b11 3
b10100 )
1#
